libmonty_hexdump/__init__.py
libmonty_hexdump/__main__.py
libmonty_hexdump/version.py
libmonty_hexdump/components/__init__.py
libmonty_hexdump/components/arguments.py
libmonty_hexdump/components/lines.py
libmonty_hexdump/components/streams.py
libmonty_hexdump/components/width.py
libmonty_hexdump-0.1.1.dist-info/LICENSE
libmonty_hexdump-0.1.1.dist-info/METADATA
libmonty_hexdump-0.1.1.dist-info/WHEEL
libmonty_hexdump-0.1.1.dist-info/entry_points.txt
libmonty_hexdump-0.1.1.dist-info/top_level.txt
libmonty_hexdump-0.1.1.dist-info/RECORD
