Metadata-Version: 2.1
Name: libmonty-hexdump
Version: 0.1.1
Summary: libmonty-hexdump - Python library - hexdump utility
Home-page: https://codeberg.org/sunarch/libmonty-hexdump
Author: András Németh (sunarch)
Author-email: sunarch@protonmail.com
Maintainer: András Németh (sunarch)
Maintainer-email: sunarch@protonmail.com
License: Mozilla Public License 2.0 (MPL 2.0)
Project-URL: Bug Tracker, https://codeberg.org/sunarch/libmonty-hexdump/issues
Keywords: libmonty,hexdump
Platform: Any
Classifier: Development Status :: 3 - Alpha
Classifier: Environment :: Console
Classifier: Intended Audience :: Developers
Classifier: Intended Audience :: End Users/Desktop
Classifier: Intended Audience :: System Administrators
Classifier: License :: OSI Approved :: Mozilla Public License 2.0 (MPL 2.0)
Classifier: Natural Language :: English
Classifier: Operating System :: OS Independent
Classifier: Programming Language :: Python :: 3
Classifier: Topic :: Software Development
Classifier: Topic :: System
Classifier: Topic :: Text Processing :: General
Classifier: Topic :: Utilities
Classifier: Typing :: Typed
Requires-Python: >=3.10
License-File: LICENSE
Requires-Dist: libmonty (==0.1.0)
Requires-Dist: libmonty-logging (==0.1.1)
